setup.py
sotong/__init__.py
sotong/api.py
sotong/event.py
sotong/log.py
sotong/sotong.py
sotong.egg-info/PKG-INFO
sotong.egg-info/SOURCES.txt
sotong.egg-info/dependency_links.txt
sotong.egg-info/requires.txt
sotong.egg-info/top_level.txt
test/test_sotong.py