Metadata-Version: 1.0
Name: sotong
Version: 0.1.6
Summary: Tiny automation tool like Jenkins, Buildbot, etc...
Home-page: UNKNOWN
Author: wak
Author-email: UNKNOWN
License: UNKNOWN
Platform: UNKNOWN
